pyidaungsu/__init__.py
pyidaungsu/tokenize.py
pyidaungsu/model/pdsdetect.ftz
pyidaungsu/model/tokenizer.crfsuite
pyidaungsu/model/lib/fasttext_pybind.cpython-38-x86_64-linux-gnu.so
pyidaungsu_numpy2-0.1.4.dist-info/LICENSE
pyidaungsu_numpy2-0.1.4.dist-info/METADATA
pyidaungsu_numpy2-0.1.4.dist-info/WHEEL
pyidaungsu_numpy2-0.1.4.dist-info/top_level.txt
pyidaungsu_numpy2-0.1.4.dist-info/RECORD
