Metadata-Version: 2.1
Name: pyidaungsu-numpy2
Version: 0.1.4
Summary: Python library for Pyidaungsu Myanmar languages
Home-page: https://github.com/kaunghtetsan275/pyidaungsu
Download-URL: https://github.com/kaunghtetsan275/pyidaungsu/archive/0.1.4.tar.gz
Author: Kaung Htet San
Author-email: kaung@htetsan.me
Classifier: Programming Language :: Python :: 3
Classifier: License :: OSI Approved :: MIT License
Classifier: Operating System :: OS Independent
Requires-Python: >=3.6
License-File: LICENSE
Requires-Dist: numpy
Requires-Dist: python-crfsuite
Requires-Dist: emoji
Requires-Dist: pybind11
Requires-Dist: fasttext-numpy2-wheel
